LICENSE
README.rst
setup.py
src/fast_scboot/__init__.py
src/fast_scboot/fast_scboot.py
src/fast_scboot/utils.py
src/fast_scboot.egg-info/PKG-INFO
src/fast_scboot.egg-info/SOURCES.txt
src/fast_scboot.egg-info/dependency_links.txt
src/fast_scboot.egg-info/top_level.txt
src/fast_scboot/c/__init__.py
src/fast_scboot/c/pytest_validator.c
src/fast_scboot/c/pytest_validator.pyx
src/fast_scboot/c/sample_index_helper.c
src/fast_scboot/c/sample_index_helper.pyx
src/fast_scboot/c/tuple_hash_function.c
src/fast_scboot/c/tuple_hash_function.pyx
src/fast_scboot/c/utils.c
src/fast_scboot/c/utils.pyx