Metadata-Version: 2.1
Name: fast-scboot
Version: 0.1b1
Summary: Fast implementation of the stratified cluster bootstrap sampling algorithm.
Home-page: https://github.com/mozjay0619/fast-scboot
Author: Jay Kim
Author-email: mozjay0619@gmail.com
License: DSB 3-clause
Platform: UNKNOWN
Classifier: Programming Language :: Python :: 3.6
Classifier: Programming Language :: Python :: 3.7
Classifier: Programming Language :: Python :: 3.8
Classifier: Programming Language :: Python :: 3.9
Requires-Python: >=3
License-File: LICENSE
